{"asof":"2026-07-23 12:03 UTC","source":"yfinance direct chain (scale=1, 8 exp <=90d)","error":"degenerate_chain","overview":{"spx_spot":34.68,"net_gex_B":null,"regime":"UNKNOWN","gamma_flip":null,"dist_to_flip_pct":null,"net_vanna_B_per_volpt":null,"net_charm_B_per_day":null},"levels":{"pin":null,"call_wall":null,"put_wall":null,"gamma_flip":null},"profile":[],"confidence":{"levels":"INVALID","regime_sign":"INVALID","note":"Bad data pull: only 15 strikes, 139282 total OI, 100350 put OI. Yahoo likely throttled the options chain. NOT a valid reading \u2014 do not use."},"diagnostics":{"n_strikes":15,"total_oi":139282,"total_put_oi":100350},"stock_validity":"INVALID_THIN_CHAIN","ticker":"IONQ"}