{"asof":"2026-07-24 11:26 UTC","source":"yfinance direct chain (scale=1, 8 exp <=90d)","overview":{"spx_spot":381.58,"net_gex_B":0.03,"regime":"Positive Gamma","gamma_flip":381.0,"dist_to_flip_pct":-0.15,"net_vanna_B_per_volpt":0.01,"net_charm_B_per_day":-0.0},"raw":{"net_gex_B":0.033,"net_vanna_B":0.01,"net_charm_B":-0.003,"calibrated":false},"levels":{"pin":{"strike":450,"net_gex_B":0.0,"coi":66643,"poi":3121},"call_wall":{"strike":390,"net_gex_B":0.001,"coi":44020,"poi":10348},"put_wall":{"strike":380,"net_gex_B":-0.0,"coi":11534,"poi":17088},"gamma_flip":381.0,"supports":[{"strike":380,"net_gex_B":-0.0,"coi":11534,"poi":17088},{"strike":375,"net_gex_B":-0.0,"coi":4201,"poi":12949},{"strike":370,"net_gex_B":-0.0,"coi":8607,"poi":21453},{"strike":365,"net_gex_B":-0.0,"coi":2217,"poi":9417},{"strike":360,"net_gex_B":-0.0,"coi":3813,"poi":20171}],"resistances":[{"strike":390,"net_gex_B":0.001,"coi":44020,"poi":10348},{"strike":400,"net_gex_B":0.0,"coi":47296,"poi":11346},{"strike":410,"net_gex_B":0.0,"coi":27481,"poi":6426},{"strike":420,"net_gex_B":0.0,"coi":33514,"poi":12459},{"strike":430,"net_gex_B":0.0,"coi":35086,"poi":3068}],"magnets":{"put":{"strike":350,"net_gex_B":-0.0,"coi":3139,"poi":25820},"call":{"strike":450,"net_gex_B":0.0,"coi":66643,"poi":3121}},"wall_threshold":0.3},"profile":[{"strike":310,"net_gex_B":-0.0,"coi":520,"poi":4798},{"strike":315,"net_gex_B":-0.0,"coi":285,"poi":3679},{"strike":320,"net_gex_B":-0.0,"coi":328,"poi":6202},{"strike":322,"net_gex_B":-0.0,"coi":3,"poi":135},{"strike":325,"net_gex_B":-0.0,"coi":266,"poi":5719},{"strike":328,"net_gex_B":-0.0,"coi":64,"poi":174},{"strike":330,"net_gex_B":-0.0,"coi":568,"poi":8938},{"strike":332,"net_gex_B":-0.0,"coi":22,"poi":154},{"strike":335,"net_gex_B":-0.0,"coi":395,"poi":5593},{"strike":338,"net_gex_B":-0.0,"coi":20,"poi":407},{"strike":340,"net_gex_B":-0.0,"coi":515,"poi":18624},{"strike":342,"net_gex_B":-0.0,"coi":11,"poi":249},{"strike":345,"net_gex_B":-0.0,"coi":539,"poi":12894},{"strike":348,"net_gex_B":-0.0,"coi":15,"poi":370},{"strike":350,"net_gex_B":-0.0,"coi":3139,"poi":25820},{"strike":352,"net_gex_B":-0.0,"coi":217,"poi":1022},{"strike":355,"net_gex_B":-0.0,"coi":1316,"poi":8749},{"strike":358,"net_gex_B":-0.0,"coi":79,"poi":2045},{"strike":360,"net_gex_B":-0.0,"coi":3813,"poi":20171},{"strike":362,"net_gex_B":-0.0,"coi":179,"poi":2679},{"strike":365,"net_gex_B":-0.0,"coi":2217,"poi":9417},{"strike":368,"net_gex_B":-0.0,"coi":249,"poi":1818},{"strike":370,"net_gex_B":-0.0,"coi":8607,"poi":21453},{"strike":372,"net_gex_B":-0.0,"coi":269,"poi":1936},{"strike":375,"net_gex_B":-0.0,"coi":4201,"poi":12949},{"strike":378,"net_gex_B":-0.001,"coi":843,"poi":3765},{"strike":380,"net_gex_B":-0.0,"coi":11534,"poi":17088},{"strike":382,"net_gex_B":0.027,"coi":2675,"poi":2434},{"strike":385,"net_gex_B":0.006,"coi":14118,"poi":16284},{"strike":388,"net_gex_B":0.0,"coi":5769,"poi":2183},{"strike":390,"net_gex_B":0.001,"coi":44020,"poi":10348},{"strike":392,"net_gex_B":0.0,"coi":9106,"poi":1201},{"strike":395,"net_gex_B":0.0,"coi":17300,"poi":9301},{"strike":398,"net_gex_B":0.0,"coi":4622,"poi":1054},{"strike":400,"net_gex_B":0.0,"coi":47296,"poi":11346},{"strike":402,"net_gex_B":0.0,"coi":4262,"poi":473},{"strike":405,"net_gex_B":0.0,"coi":15742,"poi":2541},{"strike":408,"net_gex_B":0.0,"coi":3381,"poi":51},{"strike":410,"net_gex_B":0.0,"coi":27481,"poi":6426},{"strike":412,"net_gex_B":0.0,"coi":2104,"poi":86},{"strike":415,"net_gex_B":0.0,"coi":16317,"poi":2507},{"strike":418,"net_gex_B":0.0,"coi":2339,"poi":23},{"strike":420,"net_gex_B":0.0,"coi":33514,"poi":12459},{"strike":422,"net_gex_B":0.0,"coi":3157,"poi":70},{"strike":425,"net_gex_B":0.0,"coi":15693,"poi":876},{"strike":428,"net_gex_B":0.0,"coi":1555,"poi":13},{"strike":430,"net_gex_B":0.0,"coi":35086,"poi":3068},{"strike":432,"net_gex_B":0.0,"coi":1579,"poi":39},{"strike":435,"net_gex_B":0.0,"coi":19433,"poi":637},{"strike":438,"net_gex_B":0.0,"coi":549,"poi":65},{"strike":440,"net_gex_B":0.0,"coi":29988,"poi":1994},{"strike":442,"net_gex_B":0.0,"coi":583,"poi":2},{"strike":445,"net_gex_B":0.0,"coi":8588,"poi":555},{"strike":448,"net_gex_B":0.0,"coi":169,"poi":0},{"strike":450,"net_gex_B":0.0,"coi":66643,"poi":3121},{"strike":452,"net_gex_B":0.0,"coi":2723,"poi":0},{"strike":455,"net_gex_B":0.0,"coi":9365,"poi":829},{"strike":458,"net_gex_B":0.0,"coi":164,"poi":10}],"confidence":{"levels":"high","regime_sign":"low_on_proxy","note":"SPY proxy: flip/walls reliable, net-GEX sign approximate. True SPX (IBKR) fixes sign."},"stock_validity":"ok","ticker":"MSFT"}