{"asof":"2026-07-21 11:31 UTC","source":"yfinance direct chain (scale=1, 8 exp <=90d)","overview":{"spx_spot":97.82,"net_gex_B":0.04,"regime":"Positive Gamma","gamma_flip":97.5,"dist_to_flip_pct":-0.33,"net_vanna_B_per_volpt":0.01,"net_charm_B_per_day":-0.0},"raw":{"net_gex_B":0.042,"net_vanna_B":0.012,"net_charm_B":-0.001,"calibrated":false},"levels":{"pin":{"strike":100,"net_gex_B":0.006,"coi":64129,"poi":27649},"call_wall":{"strike":98,"net_gex_B":0.036,"coi":19967,"poi":1763},"put_wall":{"strike":95,"net_gex_B":-0.0,"coi":21070,"poi":15609},"gamma_flip":97.5,"supports":[{"strike":95,"net_gex_B":-0.0,"coi":21070,"poi":15609},{"strike":90,"net_gex_B":-0.0,"coi":3783,"poi":28862},{"strike":85,"net_gex_B":-0.0,"coi":1383,"poi":15580},{"strike":80,"net_gex_B":-0.0,"coi":929,"poi":38812}],"resistances":[{"strike":98,"net_gex_B":0.036,"coi":19967,"poi":1763},{"strike":100,"net_gex_B":0.006,"coi":64129,"poi":27649},{"strike":102,"net_gex_B":0.0,"coi":34530,"poi":641}],"magnets":{"put":{"strike":80,"net_gex_B":-0.0,"coi":929,"poi":38812},"call":{"strike":100,"net_gex_B":0.006,"coi":64129,"poi":27649}},"wall_threshold":0.3},"profile":[{"strike":79,"net_gex_B":-0.0,"coi":43,"poi":1678},{"strike":80,"net_gex_B":-0.0,"coi":929,"poi":38812},{"strike":81,"net_gex_B":-0.0,"coi":96,"poi":1247},{"strike":82,"net_gex_B":-0.0,"coi":82,"poi":3400},{"strike":83,"net_gex_B":-0.0,"coi":50,"poi":1582},{"strike":84,"net_gex_B":-0.0,"coi":90,"poi":1524},{"strike":85,"net_gex_B":-0.0,"coi":1383,"poi":15580},{"strike":86,"net_gex_B":-0.0,"coi":392,"poi":6590},{"strike":87,"net_gex_B":-0.0,"coi":281,"poi":3543},{"strike":88,"net_gex_B":-0.0,"coi":420,"poi":1532},{"strike":89,"net_gex_B":-0.0,"coi":408,"poi":1341},{"strike":90,"net_gex_B":-0.0,"coi":3783,"poi":28862},{"strike":91,"net_gex_B":-0.0,"coi":600,"poi":8466},{"strike":92,"net_gex_B":-0.0,"coi":731,"poi":3281},{"strike":93,"net_gex_B":-0.0,"coi":672,"poi":1716},{"strike":94,"net_gex_B":-0.0,"coi":1105,"poi":1176},{"strike":95,"net_gex_B":-0.0,"coi":21070,"poi":15609},{"strike":96,"net_gex_B":-0.0,"coi":42029,"poi":2316},{"strike":97,"net_gex_B":-0.0,"coi":9768,"poi":953},{"strike":98,"net_gex_B":0.036,"coi":19967,"poi":1763},{"strike":99,"net_gex_B":0.0,"coi":1868,"poi":668},{"strike":100,"net_gex_B":0.006,"coi":64129,"poi":27649},{"strike":101,"net_gex_B":0.0,"coi":16145,"poi":653},{"strike":102,"net_gex_B":0.0,"coi":34530,"poi":641},{"strike":103,"net_gex_B":0.0,"coi":13480,"poi":413},{"strike":104,"net_gex_B":0.0,"coi":11118,"poi":335},{"strike":105,"net_gex_B":0.0,"coi":14026,"poi":8167},{"strike":106,"net_gex_B":0.0,"coi":2172,"poi":338},{"strike":107,"net_gex_B":0.0,"coi":1641,"poi":1218},{"strike":108,"net_gex_B":0.0,"coi":2020,"poi":935},{"strike":109,"net_gex_B":0.0,"coi":971,"poi":138},{"strike":110,"net_gex_B":0.0,"coi":17383,"poi":9819},{"strike":111,"net_gex_B":0.0,"coi":1177,"poi":121},{"strike":112,"net_gex_B":0.0,"coi":1975,"poi":186},{"strike":113,"net_gex_B":0.0,"coi":638,"poi":150},{"strike":114,"net_gex_B":0.0,"coi":537,"poi":169},{"strike":115,"net_gex_B":0.0,"coi":12230,"poi":9408},{"strike":116,"net_gex_B":0.0,"coi":1741,"poi":88},{"strike":117,"net_gex_B":0.0,"coi":586,"poi":155}],"confidence":{"levels":"high","regime_sign":"low_on_proxy","note":"SPY proxy: flip/walls reliable, net-GEX sign approximate. True SPX (IBKR) fixes sign."},"stock_validity":"ok","ticker":"MSTR"}