{"asof":"2026-07-21 11:10 UTC","source":"yfinance direct chain (scale=1, 8 exp <=90d)","overview":{"spx_spot":865.46,"net_gex_B":0.01,"regime":"Positive Gamma","gamma_flip":867.5,"dist_to_flip_pct":0.24,"net_vanna_B_per_volpt":0.01,"net_charm_B_per_day":-0.0},"raw":{"net_gex_B":0.011,"net_vanna_B":0.007,"net_charm_B":-0.0,"calibrated":false},"levels":{"pin":{"strike":1000,"net_gex_B":0.0,"coi":20504,"poi":6619},"call_wall":{"strike":900,"net_gex_B":0.0,"coi":11189,"poi":4687},"put_wall":{"strike":850,"net_gex_B":-0.0,"coi":1949,"poi":14723},"gamma_flip":867.5,"supports":[{"strike":850,"net_gex_B":-0.0,"coi":1949,"poi":14723},{"strike":825,"net_gex_B":-0.0,"coi":144,"poi":6485},{"strike":820,"net_gex_B":-0.0,"coi":1008,"poi":7252},{"strike":815,"net_gex_B":-0.0,"coi":181,"poi":14112},{"strike":800,"net_gex_B":-0.0,"coi":2557,"poi":18842}],"resistances":[{"strike":900,"net_gex_B":0.0,"coi":11189,"poi":4687},{"strike":1000,"net_gex_B":0.0,"coi":20504,"poi":6619}],"magnets":{"put":{"strike":800,"net_gex_B":-0.0,"coi":2557,"poi":18842},"call":{"strike":1000,"net_gex_B":0.0,"coi":20504,"poi":6619}},"wall_threshold":0.3},"profile":[{"strike":692,"net_gex_B":-0.0,"coi":0,"poi":151},{"strike":695,"net_gex_B":-0.0,"coi":6,"poi":1304},{"strike":698,"net_gex_B":-0.0,"coi":0,"poi":187},{"strike":700,"net_gex_B":-0.0,"coi":1428,"poi":16477},{"strike":702,"net_gex_B":-0.0,"coi":7,"poi":223},{"strike":705,"net_gex_B":-0.0,"coi":19,"poi":353},{"strike":708,"net_gex_B":-0.0,"coi":0,"poi":182},{"strike":710,"net_gex_B":-0.0,"coi":60,"poi":902},{"strike":712,"net_gex_B":-0.0,"coi":0,"poi":217},{"strike":715,"net_gex_B":-0.0,"coi":6,"poi":464},{"strike":718,"net_gex_B":-0.0,"coi":2,"poi":124},{"strike":720,"net_gex_B":-0.0,"coi":41,"poi":1675},{"strike":722,"net_gex_B":-0.0,"coi":0,"poi":53},{"strike":725,"net_gex_B":-0.0,"coi":54,"poi":1836},{"strike":728,"net_gex_B":-0.0,"coi":1,"poi":225},{"strike":730,"net_gex_B":-0.0,"coi":103,"poi":4630},{"strike":732,"net_gex_B":-0.0,"coi":0,"poi":127},{"strike":735,"net_gex_B":-0.0,"coi":10,"poi":763},{"strike":738,"net_gex_B":-0.0,"coi":12,"poi":339},{"strike":740,"net_gex_B":-0.0,"coi":116,"poi":2036},{"strike":742,"net_gex_B":-0.0,"coi":5,"poi":296},{"strike":745,"net_gex_B":-0.0,"coi":37,"poi":852},{"strike":748,"net_gex_B":-0.0,"coi":0,"poi":328},{"strike":750,"net_gex_B":-0.0,"coi":993,"poi":12284},{"strike":755,"net_gex_B":-0.0,"coi":131,"poi":1453},{"strike":760,"net_gex_B":-0.0,"coi":376,"poi":1879},{"strike":765,"net_gex_B":-0.0,"coi":22,"poi":629},{"strike":770,"net_gex_B":-0.0,"coi":56,"poi":1797},{"strike":775,"net_gex_B":-0.0,"coi":61,"poi":3600},{"strike":780,"net_gex_B":-0.0,"coi":139,"poi":2113},{"strike":785,"net_gex_B":-0.0,"coi":60,"poi":1300},{"strike":790,"net_gex_B":-0.0,"coi":95,"poi":11906},{"strike":795,"net_gex_B":-0.0,"coi":210,"poi":1255},{"strike":800,"net_gex_B":-0.0,"coi":2557,"poi":18842},{"strike":805,"net_gex_B":-0.0,"coi":110,"poi":2006},{"strike":810,"net_gex_B":-0.0,"coi":436,"poi":1326},{"strike":815,"net_gex_B":-0.0,"coi":181,"poi":14112},{"strike":820,"net_gex_B":-0.0,"coi":1008,"poi":7252},{"strike":825,"net_gex_B":-0.0,"coi":144,"poi":6485},{"strike":830,"net_gex_B":-0.0,"coi":713,"poi":1326},{"strike":835,"net_gex_B":-0.0,"coi":126,"poi":1052},{"strike":840,"net_gex_B":-0.0,"coi":981,"poi":3255},{"strike":845,"net_gex_B":-0.0,"coi":435,"poi":714},{"strike":850,"net_gex_B":-0.0,"coi":1949,"poi":14723},{"strike":855,"net_gex_B":-0.0,"coi":408,"poi":1091},{"strike":860,"net_gex_B":-0.0,"coi":849,"poi":1296},{"strike":865,"net_gex_B":-0.0,"coi":465,"poi":515},{"strike":870,"net_gex_B":0.011,"coi":1358,"poi":3708},{"strike":875,"net_gex_B":0.0,"coi":1082,"poi":1067},{"strike":880,"net_gex_B":0.0,"coi":1220,"poi":5258},{"strike":885,"net_gex_B":0.0,"coi":1196,"poi":1228},{"strike":890,"net_gex_B":0.0,"coi":1261,"poi":1372},{"strike":895,"net_gex_B":0.0,"coi":1003,"poi":1470},{"strike":900,"net_gex_B":0.0,"coi":11189,"poi":4687},{"strike":905,"net_gex_B":0.0,"coi":1632,"poi":499},{"strike":910,"net_gex_B":0.0,"coi":1314,"poi":1403},{"strike":915,"net_gex_B":0.0,"coi":2707,"poi":431},{"strike":920,"net_gex_B":0.0,"coi":1729,"poi":1700},{"strike":925,"net_gex_B":0.0,"coi":1169,"poi":815},{"strike":930,"net_gex_B":0.0,"coi":2967,"poi":1173},{"strike":932,"net_gex_B":0.0,"coi":101,"poi":97},{"strike":935,"net_gex_B":0.0,"coi":789,"poi":1582},{"strike":938,"net_gex_B":0.0,"coi":161,"poi":146},{"strike":940,"net_gex_B":0.0,"coi":1998,"poi":1104},{"strike":942,"net_gex_B":0.0,"coi":290,"poi":52},{"strike":945,"net_gex_B":0.0,"coi":481,"poi":492},{"strike":948,"net_gex_B":0.0,"coi":97,"poi":248},{"strike":950,"net_gex_B":0.0,"coi":5012,"poi":9232},{"strike":952,"net_gex_B":0.0,"coi":150,"poi":34},{"strike":955,"net_gex_B":0.0,"coi":1148,"poi":505},{"strike":960,"net_gex_B":0.0,"coi":3146,"poi":1229},{"strike":965,"net_gex_B":0.0,"coi":755,"poi":279},{"strike":970,"net_gex_B":0.0,"coi":4060,"poi":423},{"strike":975,"net_gex_B":0.0,"coi":1534,"poi":698},{"strike":980,"net_gex_B":0.0,"coi":2942,"poi":1497},{"strike":985,"net_gex_B":0.0,"coi":772,"poi":455},{"strike":990,"net_gex_B":0.0,"coi":1237,"poi":844},{"strike":995,"net_gex_B":0.0,"coi":744,"poi":987},{"strike":1000,"net_gex_B":0.0,"coi":20504,"poi":6619},{"strike":1002,"net_gex_B":0.0,"coi":171,"poi":0},{"strike":1005,"net_gex_B":0.0,"coi":2406,"poi":123},{"strike":1008,"net_gex_B":0.0,"coi":77,"poi":0},{"strike":1010,"net_gex_B":0.0,"coi":1882,"poi":520},{"strike":1012,"net_gex_B":0.0,"coi":104,"poi":2},{"strike":1015,"net_gex_B":0.0,"coi":985,"poi":109},{"strike":1018,"net_gex_B":0.0,"coi":90,"poi":0},{"strike":1020,"net_gex_B":0.0,"coi":2147,"poi":860},{"strike":1022,"net_gex_B":0.0,"coi":125,"poi":0},{"strike":1025,"net_gex_B":0.0,"coi":1073,"poi":38},{"strike":1030,"net_gex_B":0.0,"coi":1664,"poi":802},{"strike":1035,"net_gex_B":0.0,"coi":3425,"poi":73}],"confidence":{"levels":"high","regime_sign":"low_on_proxy","note":"SPY proxy: flip/walls reliable, net-GEX sign approximate. True SPX (IBKR) fixes sign."},"stock_validity":"ok","ticker":"MU"}